scholar/__init__.py
scholar/__main__.py
scholar/cache.py
scholar/cli.py
scholar/enrich.py
scholar/llm_review.py
scholar/notes.py
scholar/pdf.py
scholar/providers.py
scholar/questionary.py
scholar/review.py
scholar/scholar.py
scholar/tui.py
scholar/utils.py
scholarcli-1.9.dist-info/licenses/LICENSE
snowball/__init__.py
snowball/cli.py
snowball/models.py
snowball/paper_utils.py
snowball/snowballing.py
snowball/visualization.py
snowball/apis/__init__.py
snowball/apis/aggregator.py
snowball/apis/arxiv.py
snowball/apis/base.py
snowball/apis/crossref.py
snowball/apis/google_scholar.py
snowball/apis/openalex.py
snowball/apis/opencitations.py
snowball/apis/semantic_scholar.py
snowball/exporters/__init__.py
snowball/exporters/bibtex.py
snowball/exporters/csv_exporter.py
snowball/exporters/tikz.py
snowball/filters/__init__.py
snowball/filters/filter_engine.py
snowball/parsers/__init__.py
snowball/parsers/pdf_parser.py
snowball/scoring/__init__.py
snowball/scoring/base.py
snowball/scoring/llm_scorer.py
snowball/scoring/tfidf_scorer.py
snowball/storage/__init__.py
snowball/storage/json_storage.py
snowball/tui/__init__.py
snowball/tui/app.py
tuxedo/__init__.py
tuxedo/analysis.py
tuxedo/cli.py
tuxedo/clustering.py
tuxedo/database.py
tuxedo/grobid.py
tuxedo/logging.py
tuxedo/models.py
tuxedo/project.py
tuxedo/tui.py
scholarcli-1.9.dist-info/METADATA
scholarcli-1.9.dist-info/WHEEL
scholarcli-1.9.dist-info/entry_points.txt
scholarcli-1.9.dist-info/top_level.txt
scholarcli-1.9.dist-info/RECORD
