Metadata-Version: 2.4
Name: scholarcli
Version: 1.9
Summary: A tool for structured literature searches across bibliographic databases
Author-email: Daniel Bosk <dbosk@kth.se>, Ric Glassey <glassey@kth.se>
License-Expression: MIT
Requires-Python: >=3.12
License-File: LICENSE
Requires-Dist: requests>=2.32.5
Requires-Dist: typer>=0.21.0
Requires-Dist: rich>=14.2.0
Requires-Dist: pyalex>=0.19
Requires-Dist: arxiv>=2.1.0
Requires-Dist: cachetools>=6.2.4
Requires-Dist: platformdirs>=4.5.1
Requires-Dist: textual>=6.11.0
Requires-Dist: pypandoc>=1.14
Requires-Dist: click>=8.0.0
Requires-Dist: llm>=0.19
Requires-Dist: llm-openai-plugin>=0.7
Requires-Dist: llm-gpt4all>=0.4
Requires-Dist: llm-azure>=2.1
Requires-Dist: llm-anthropic>=0.23
Requires-Dist: llm-gemini>=0.28.2
Requires-Dist: pypdfium2>=4.26.0
Requires-Dist: bibtexparser>=1.4.0
Requires-Dist: pandas>=2.0.0
Requires-Dist: pydantic>=2.0.0
Requires-Dist: python-dotenv>=1.0.0
Requires-Dist: httpx>=0.25.0
Requires-Dist: grobid-client-python>=0.1.0
Requires-Dist: scholarly>=1.7.0
Requires-Dist: openai>=1.0.0
Requires-Dist: pyyaml>=6.0
Requires-Dist: questionary>=2.0.0
Requires-Dist: llm-github-copilot>=0.3.1
Dynamic: license-file
